{"response":{"station":[{"x":139.507472,"next":"五月台","prev":null,"y":35.603709,"line":"小田急多摩線","postal":"2150004","name":"新百合ヶ丘","prefecture":"神奈川県"},{"x":139.493389,"next":"栗平","prev":"新百合ヶ丘","y":35.600229,"line":"小田急多摩線","postal":"2150025","name":"五月台","prefecture":"神奈川県"},{"x":139.481292,"next":"黒川","prev":"五月台","y":35.605748,"line":"小田急多摩線","postal":"2150024","name":"栗平","prefecture":"神奈川県"},{"x":139.470748,"next":"はるひ野","prev":"栗平","y":35.613138,"line":"小田急多摩線","postal":"2150034","name":"黒川","prefecture":"神奈川県"},{"x":139.464979,"next":"小田急永山","prev":"黒川","y":35.618409,"line":"小田急多摩線","postal":"2150036","name":"はるひ野","prefecture":"神奈川県"},{"x":139.448132,"next":"小田急多摩センター","prev":"はるひ野","y":35.629896,"line":"小田急多摩線","postal":"2060025","name":"小田急永山","prefecture":"東京都"},{"x":139.424375,"next":"唐木田","prev":"小田急永山","y":35.624933,"line":"小田急多摩線","postal":"2060033","name":"小田急多摩センター","prefecture":"東京都"},{"x":139.411672,"next":null,"prev":"小田急多摩センター","y":35.616565,"line":"小田急多摩線","postal":"2060036","name":"唐木田","prefecture":"東京都"}]}}
