{"response":{"station":[{"x":139.531392,"next":"富士見町","prev":null,"y":35.35252,"line":"湘南モノレール","postal":"2470056","name":"大船","prefecture":"神奈川県"},{"x":139.529321,"next":"湘南町屋","prev":"大船","y":35.345349,"line":"湘南モノレール","postal":"2470061","name":"富士見町","prefecture":"神奈川県"},{"x":139.522719,"next":"湘南深沢","prev":"富士見町","y":35.337854,"line":"湘南モノレール","postal":"2470065","name":"湘南町屋","prefecture":"神奈川県"},{"x":139.518911,"next":"西鎌倉","prev":"湘南町屋","y":35.332976,"line":"湘南モノレール","postal":"2470063","name":"湘南深沢","prefecture":"神奈川県"},{"x":139.504306,"next":"片瀬山","prev":"湘南深沢","y":35.319395,"line":"湘南モノレール","postal":"2480035","name":"西鎌倉","prefecture":"神奈川県"},{"x":139.496267,"next":"目白山下","prev":"西鎌倉","y":35.317315,"line":"湘南モノレール","postal":"2480035","name":"片瀬山","prefecture":"神奈川県"},{"x":139.491516,"next":"湘南江の島","prev":"片瀬山","y":35.314068,"line":"湘南モノレール","postal":"2510032","name":"目白山下","prefecture":"神奈川県"},{"x":139.487813,"next":null,"prev":"目白山下","y":35.311873,"line":"湘南モノレール","postal":"2510032","name":"湘南江の島","prefecture":"神奈川県"}]}}
